<?xml version="1.0"?>
<BuildLog xmlns:xsi="http://www.w3.org/2001/XMLSchema-instance" xmlns:xsd="http://www.w3.org/2001/XMLSchema">
  <ProjectInfo>
    <Name>Project</Name>
    <LastWriteTime>2017-11-08T00:20:33.046567Z</LastWriteTime>
    <LastKnownProtectionLevel>EncryptSensitiveWithUserKey</LastKnownProtectionLevel>
  </ProjectInfo>
  <LastBuildInfos>
    <ProjectBuildItemInfo>
      <Name>DatePackage.dtsx</Name>
      <LastWriteTime>2017-10-25T22:27:00.6811709Z</LastWriteTime>
      <LastKnownProtectionLevel>EncryptSensitiveWithUserKey</LastKnownProtectionLevel>
    </ProjectBuildItemInfo>
    <ProjectBuildItemInfo>
      <Name>ProductPackage.dtsx</Name>
      <LastWriteTime>2017-10-21T23:00:03.7668805Z</LastWriteTime>
      <LastKnownProtectionLevel>EncryptSensitiveWithUserKey</LastKnownProtectionLevel>
    </ProjectBuildItemInfo>
    <ProjectBuildItemInfo>
      <Name>CustomerPackage.dtsx</Name>
      <LastWriteTime>2017-11-09T11:52:13.9823143Z</LastWriteTime>
      <LastKnownProtectionLevel>EncryptSensitiveWithUserKey</LastKnownProtectionLevel>
    </ProjectBuildItemInfo>
    <ProjectBuildItemInfo>
      <Name>MasterPackage.dtsx</Name>
      <LastWriteTime>2017-10-25T22:33:50.8223057Z</LastWriteTime>
      <LastKnownProtectionLevel>EncryptSensitiveWithUserKey</LastKnownProtectionLevel>
    </ProjectBuildItemInfo>
  </LastBuildInfos>
</BuildLog>